edc_randomization/__init__.py
edc_randomization/admin.py
edc_randomization/admin_site.py
edc_randomization/apps.py
edc_randomization/auth_objects.py
edc_randomization/auths.py
edc_randomization/blinding.py
edc_randomization/choices.py
edc_randomization/constants.py
edc_randomization/decorators.py
edc_randomization/model_mixins.py
edc_randomization/randomization_list_importer.py
edc_randomization/randomization_list_verifier.py
edc_randomization/randomizer.py
edc_randomization/randomizers.py
edc_randomization/site_randomizers.py
edc_randomization/system_checks.py
edc_randomization/urls.py
edc_randomization/utils.py
edc_randomization/views.py
edc_randomization/migrations/0001_initial.py
edc_randomization/migrations/0002_historicalrandomizationlist.py
edc_randomization/migrations/0003_auto_20191024_0426.py
edc_randomization/migrations/0004_auto_20191108_0752.py
edc_randomization/migrations/0005_auto_20200202_2301.py
edc_randomization/migrations/0006_auto_20200213_2055.py
edc_randomization/migrations/0007_auto_20200513_0023.py
edc_randomization/migrations/0008_auto_20220704_1841.py
edc_randomization/migrations/0009_edcpermissions.py
edc_randomization/migrations/0010_alter_randomizationlist_options.py
edc_randomization/migrations/0011_alter_edcpermissions_device_created_and_more.py
edc_randomization/migrations/0012_alter_randomizationlist_options_and_more.py
edc_randomization/migrations/__init__.py
edc_randomization/models/__init__.py
edc_randomization/models/edc_permissions.py
edc_randomization/models/randomization_list.py
edc_randomization/tests/__init__.py
edc_randomization/tests/make_test_list.py
edc_randomization/tests/models.py
edc_randomization/tests/randomizers.py
edc_randomization/tests/test_settings.py
edc_randomization/tests/testcase_mixin.py
edc_randomization/tests/etc/user-aes-local.key
edc_randomization/tests/etc/user-aes-restricted.key
edc_randomization/tests/etc/user-rsa-local-private.pem
edc_randomization/tests/etc/user-rsa-local-public.pem
edc_randomization-1.0.4.dist-info/licenses/AUTHORS.rst
edc_randomization-1.0.4.dist-info/licenses/LICENSE
edc_randomization-1.0.4.dist-info/METADATA
edc_randomization-1.0.4.dist-info/WHEEL
edc_randomization-1.0.4.dist-info/top_level.txt
edc_randomization-1.0.4.dist-info/RECORD
